rgb_colorizer.py
rgb_colorizer-0.0.6.dist-info/LICENSE
rgb_colorizer-0.0.6.dist-info/METADATA
rgb_colorizer-0.0.6.dist-info/WHEEL
rgb_colorizer-0.0.6.dist-info/top_level.txt
rgb_colorizer-0.0.6.dist-info/RECORD
