Metadata-Version: 2.1
Name: rgb-colorizer
Version: 0.0.6
Summary: A small package for coloring text in console
Author: Vlad Bilskiy
Project-URL: Homepage, https://github.com/hittiks/rgb-colorizer
Project-URL: Bug Tracker, https://github.com/hittiks/rgb-colorizer/issues
Classifier: Programming Language :: Python :: 3
Classifier: License :: OSI Approved :: MIT License
Classifier: Operating System :: OS Independent
Requires-Python: >=3.7
License-File: LICENSE
